odoo/addons/storage_image/README.rst
odoo/addons/storage_image/__init__.py
odoo/addons/storage_image/__manifest__.py
odoo/addons/storage_image/data/ir_parameter.xml
odoo/addons/storage_image/i18n/storage_image.pot
odoo/addons/storage_image/models/__init__.py
odoo/addons/storage_image/models/image_relation_abstract.py
odoo/addons/storage_image/models/storage_file.py
odoo/addons/storage_image/models/storage_image.py
odoo/addons/storage_image/readme/CONTRIBUTORS.rst
odoo/addons/storage_image/readme/DESCRIPTION.rst
odoo/addons/storage_image/security/ir.model.access.csv
odoo/addons/storage_image/security/ir_rule.xml
odoo/addons/storage_image/security/res_group.xml
odoo/addons/storage_image/static/description/icon.png
odoo/addons/storage_image/static/description/index.html
odoo/addons/storage_image/static/src/css/image_handle.css
odoo/addons/storage_image/static/src/js/image_handle.js
odoo/addons/storage_image/static/src/js/storage_image.js
odoo/addons/storage_image/tests/__init__.py
odoo/addons/storage_image/tests/test_storage_image.py
odoo/addons/storage_image/tests/static/akretion-logo.png
odoo/addons/storage_image/views/js.xml
odoo/addons/storage_image/views/storage_image_view.xml
odoo12_addon_storage_image-12.0.2.4.2.dist-info/METADATA
odoo12_addon_storage_image-12.0.2.4.2.dist-info/WHEEL
odoo12_addon_storage_image-12.0.2.4.2.dist-info/top_level.txt
odoo12_addon_storage_image-12.0.2.4.2.dist-info/RECORD
